odeanimate/__init__.py
odeanimate/array.py
odeanimate/codomain.py
odeanimate/constants.py
odeanimate/curve.py
odeanimate/domains.py
odeanimate/fields.py
odeanimate/jupyter.py
odeanimate/matrix.py
odeanimate/meta.py
odeanimate/utils.py
odeanimate/vector.py
odeanimate/methods/__init__.py
odeanimate/methods/curves2D.py
odeanimate/methods/geometry.py
odeanimate/methods/integration.py
odeanimate/methods/ode.py
odeanimate/methods/polynomial.py
odeanimate/plots/__init__.py
odeanimate/plots/axes.py
odeanimate/plots/integrals.py
odeanimate/plots/ode.py
odeanimate/plots/vectors.py
odeanimate-0.0.10.dist-info/LICENSE.txt
odeanimate-0.0.10.dist-info/METADATA
odeanimate-0.0.10.dist-info/WHEEL
odeanimate-0.0.10.dist-info/top_level.txt
odeanimate-0.0.10.dist-info/RECORD
