Metadata-Version: 2.1
Name: odeanimate
Version: 0.0.10
Summary: A module for useful quick mathematical calculation, plotting and animation.
Author-email: Miguel Alejandro Salgado Zapien <ekiim@ekiim.xyz>
License: GPL-2.0
Project-URL: Homepage, https://odeanimate.ekiim.xyz
Project-URL: Source, https://github.com/ekiim/odeanimate
Classifier: Development Status :: 2 - Pre-Alpha
Classifier: Intended Audience :: Education
Classifier: Intended Audience :: Science/Research
Classifier: License :: OSI Approved :: GNU General Public License v2 (GPLv2)
Classifier: Programming Language :: Python :: 3.11
Classifier: Topic :: Scientific/Engineering :: Mathematics
Classifier: Topic :: Scientific/Engineering :: Physics
Requires-Python: >=3.11
License-File: LICENSE.txt
Requires-Dist: matplotlib
